srt_trans/__init__.py
srt_trans/cli.py
srt_trans-1.0.11.dist-info/LICENSE
srt_trans-1.0.11.dist-info/METADATA
srt_trans-1.0.11.dist-info/WHEEL
srt_trans-1.0.11.dist-info/entry_points.txt
srt_trans-1.0.11.dist-info/top_level.txt
srt_trans-1.0.11.dist-info/RECORD
