Metadata-Version: 2.1
Name: srt-trans
Version: 1.0.11
Summary: A simple translator for any SubRip(.srt) files.
Home-page: https://github.com/bumblezhou/srt_trans
Author: Jack
Author-email: bumble.zhou@gmail.com
License: MIT
Classifier: License :: OSI Approved :: MIT License
Classifier: Programming Language :: Python :: 3.8
Classifier: Programming Language :: Python :: 3.9
Classifier: Programming Language :: Python :: 3.10
Classifier: Programming Language :: Python :: 3.11
Classifier: Programming Language :: Python :: 3.12
License-File: LICENSE
Requires-Dist: requests (>=2.32.3)
Requires-Dist: urllib3 (>=2.2.3)
Requires-Dist: pysrt (>=1.1.2)
Requires-Dist: ffmpeg-python (==0.2.0)
